ifstat
