Metadata-Version: 1.0
Name: ifstat
Version: 1.0.3
Summary: Display simple throughput statistics for network interface controllers. Requires Linux kernel >= 2.6
Home-page: UNKNOWN
Author: Michael Jenny
Author-email: michael.jenny@projekt-und-partner.de
License: MIT license
Keywords: bandwidth,throughput,network,monitoring,traffic
Platform: UNKNOWN
